inelsmqtt/__init__.py
inelsmqtt/config.py
inelsmqtt/const.py
inelsmqtt/discovery.py
inelsmqtt/mqtt_client.py
inelsmqtt/util.py
inelsmqtt/devices/__init__.py
inelsmqtt/devices/switch.py
tests/__init__.py
tests/const.py
tests/discovery_test.py
tests/inels_mqtt_test.py
tests/online_test.py
tests/devices/__init__.py
tests/devices/device_test.py
elkoep_mqtt-0.2.32.dist-info/LICENSE
elkoep_mqtt-0.2.32.dist-info/METADATA
elkoep_mqtt-0.2.32.dist-info/WHEEL
elkoep_mqtt-0.2.32.dist-info/top_level.txt
elkoep_mqtt-0.2.32.dist-info/RECORD
