Metadata-Version: 2.1
Name: elkoep-mqtt
Version: 0.2.32
Summary: Python library for iNELS mqtt protocol
Home-page: https://github.com/epdevlab/elkoep-mqtt
Author: Elko EP s.r.o.
Author-email: epdevlab@gmail.com
License: MIT
Keywords: iNels,Elko EP,Home assistant integration
Classifier: License :: OSI Approved :: MIT License
Classifier: Programming Language :: Python :: 3
Classifier: Programming Language :: Python :: 3.9
License-File: LICENSE
